sciencedb/__init__.py
sciencedb/client.py
sciencedb/errors.py
sciencedb/types.py
sciencedb/api/__init__.py
sciencedb/api/open_api_controller/__init__.py
sciencedb/api/open_api_controller/harvest_using_get.py
sciencedb/api/open_api_controller/json_using_get.py
sciencedb/api/open_api_controller/metrics_using_get.py
sciencedb/api/open_api_controller/search_using_get.py
sciencedb/api/sushi_controller/__init__.py
sciencedb/api/sushi_controller/get_api_status.py
sciencedb/api/sushi_controller/get_report_by_id_using_get.py
sciencedb/api/sushi_controller/get_reports.py
sciencedb/models/__init__.py
sciencedb/models/api_result_metrics_result.py
sciencedb/models/api_result_search_result.py
sciencedb/models/counter_dataset_attributes.py
sciencedb/models/counter_dataset_attributes_type.py
sciencedb/models/counter_dataset_contributors.py
sciencedb/models/counter_dataset_contributors_type.py
sciencedb/models/counter_dataset_dates.py
sciencedb/models/counter_dataset_dates_type.py
sciencedb/models/counter_dataset_identifiers.py
sciencedb/models/counter_dataset_identifiers_type.py
sciencedb/models/counter_dataset_instance.py
sciencedb/models/counter_dataset_instance_access_method.py
sciencedb/models/counter_dataset_instance_metric_type.py
sciencedb/models/counter_dataset_performance.py
sciencedb/models/counter_dataset_period.py
sciencedb/models/counter_dataset_report.py
sciencedb/models/counter_dataset_usage.py
sciencedb/models/counter_dataset_usage_data_type.py
sciencedb/models/counter_publisher_identifiers.py
sciencedb/models/counter_publisher_identifiers_type.py
sciencedb/models/metrics_result.py
sciencedb/models/search_record.py
sciencedb/models/search_result.py
sciencedb/models/sushi_error_model.py
sciencedb/models/sushi_error_model_severity.py
sciencedb/models/sushi_page_meta.py
sciencedb/models/sushi_report.py
sciencedb/models/sushi_report_header.py
sciencedb/models/sushi_report_header_report_attributes_item.py
sciencedb/models/sushi_report_header_report_filters_item.py
funapi_sciencedb-1.0.1.dist-info/LICENSE
funapi_sciencedb-1.0.1.dist-info/METADATA
funapi_sciencedb-1.0.1.dist-info/WHEEL
funapi_sciencedb-1.0.1.dist-info/top_level.txt
funapi_sciencedb-1.0.1.dist-info/RECORD
